odoo8_addon_logistic_order_multicurrency-8.0.0.1.0-py2.7-nspkg.pth
odoo_addons/logistic_order_multicurrency/__openerp__.py
odoo_addons/logistic_order_multicurrency/__init__.py
odoo_addons/logistic_order_multicurrency/README.rst
odoo_addons/logistic_order_multicurrency/view/sale_order.xml
odoo_addons/logistic_order_multicurrency/i18n/logistic_order_multicurrency.pot
odoo_addons/logistic_order_multicurrency/i18n/fr.po
odoo_addons/logistic_order_multicurrency/model/sale_order.py
odoo_addons/logistic_order_multicurrency/model/__init__.py
odoo_addons/logistic_order_multicurrency/tests/test_amount_total_co.py
odoo_addons/logistic_order_multicurrency/tests/__init__.py
odoo8_addon_logistic_order_multicurrency-8.0.0.1.0.dist-info/top_level.txt
odoo8_addon_logistic_order_multicurrency-8.0.0.1.0.dist-info/WHEEL
odoo8_addon_logistic_order_multicurrency-8.0.0.1.0.dist-info/RECORD
odoo8_addon_logistic_order_multicurrency-8.0.0.1.0.dist-info/metadata.json
odoo8_addon_logistic_order_multicurrency-8.0.0.1.0.dist-info/DESCRIPTION.rst
odoo8_addon_logistic_order_multicurrency-8.0.0.1.0.dist-info/METADATA
odoo8_addon_logistic_order_multicurrency-8.0.0.1.0.dist-info/namespace_packages.txt
